pydatapipes/__init__.py
pydatapipes/pipes.py
pydatapipes-0.1.0.dist-info/DESCRIPTION.rst
pydatapipes-0.1.0.dist-info/METADATA
pydatapipes-0.1.0.dist-info/RECORD
pydatapipes-0.1.0.dist-info/WHEEL
pydatapipes-0.1.0.dist-info/metadata.json
pydatapipes-0.1.0.dist-info/top_level.txt
