Metadata-Version: 2.0
Name: pydatapipes
Version: 0.1.0
Summary: Python data pipelines
Home-page: https://github.com/janschulz/pydatapipes
Author: Jan Schulz
Author-email: jasc@gmx.net
License: MIT license
Keywords: pydatapipes
Platform: UNKNOWN
Classifier: Development Status :: 2 - Pre-Alpha
Classifier: Intended Audience :: Developers
Classifier: License :: OSI Approved :: MIT License
Classifier: Natural Language :: English
Classifier: Programming Language :: Python :: 2
Classifier: Programming Language :: Python :: 2.7
Classifier: Programming Language :: Python :: 3
Classifier: Programming Language :: Python :: 3.4
Classifier: Programming Language :: Python :: 3.5
Requires-Dist: singledispatch; python_version == "2.7"
